{
	"comments": [],
	"credits": 6.0,
	"department": "ENGL",
	"id": "ENGL 225.00",
	"instructors": [
		"Susan Jaret McKinstry"
	],
	"number": "225.00",
	"offerings": {
		"locations": [
			"Weitz Center 233"
		],
		"times": [
			{
				"day": "Mo",
				"end": "12:20pm",
				"start": "11:10am"
			},
			{
				"day": "We",
				"end": "12:20pm",
				"start": "11:10am"
			},
			{
				"day": "Fr",
				"end": "1:00pm",
				"start": "12:00pm"
			}
		]
	},
	"prerequisites": "None",
	"requirements": [
		{
			"code": "LA",
			"name": "Literary/Artistic Analysis"
		},
		{
			"code": "WR2",
			"name": "Writing Rich 2"
		},
		{
			"code": "IS",
			"name": "International Studies"
		}
	],
	"scnc": null,
	"size": {
		"registered": 20,
		"total": 25,
		"waitlist": 0
	},
	"status": "Open",
	"summary": null,
	"synonym": "45592",
	"tags": [
		{
			"code": "ENGLHE2",
			"name": "ENGL Hist Era 2"
		},
		{
			"code": "ENGLT1",
			"name": "ENGL Tradition 1"
		}
	],
	"title": "'Public Offenders': Pre-Raphaelites and Bloomsbury Group"
}
