{
	"comments": [
		"Extra Time Required"
	],
	"credits": 6.0,
	"department": "GEOL",
	"id": "2002WI GEOL 265.00",
	"instructors": [
		"William S Dinklage"
	],
	"number": "265",
	"offerings": {
		"locations": [
			"Mudd 66"
		],
		"times": [
			{
				"day": "Mo",
				"end": "11:00am",
				"start": "9:50am"
			},
			{
				"day": "We",
				"end": "11:00am",
				"start": "9:50am"
			},
			{
				"day": "Fr",
				"end": "10:40am",
				"start": "9:40am"
			}
		]
	},
	"prerequisites": null,
	"requirements": [],
	"scnc": null,
	"section": "00",
	"semester": "WI",
	"size": {
		"registered": 6,
		"total": 20,
		"waitlist": 0
	},
	"status": "Open",
	"summary": null,
	"synonym": "2743",
	"tags": [],
	"title": "Structural Geology",
	"type": "Course",
	"year": 2002
}
