{
	"comments": [],
	"credits": 6.0,
	"department": "PE",
	"id": "PE 332.00",
	"instructors": [
		"Jessica J Mueller"
	],
	"number": "332.00",
	"offerings": {
		"locations": [
			"Recreation Center 225"
		],
		"times": [
			{
				"day": "Mo",
				"end": "11:00am",
				"start": "9:50am"
			},
			{
				"day": "We",
				"end": "11:00am",
				"start": "9:50am"
			},
			{
				"day": "Fr",
				"end": "10:40am",
				"start": "9:40am"
			}
		]
	},
	"prerequisites": null,
	"requirements": [],
	"scnc": null,
	"size": {
		"registered": 18,
		"total": 20,
		"waitlist": 0
	},
	"status": "Closed",
	"summary": "Research shows that the most successful athletes are those who are able to",
	"synonym": "34797",
	"tags": [],
	"title": "Foundations of Sport Psychology and Performance Mentality"
}
