{
	"comments": [],
	"credits": 6.0,
	"id": "2017WI ARBC 102.00",
	"instructors": [
		"Zaki A Haidar"
	],
	"number": "102",
	"offerings": {
		"locations": [
			"Language & Dining Center 330"
		],
		"times": [
			{
				"day": "Mo",
				"end": "3:00pm",
				"start": "1:50pm"
			},
			{
				"day": "Tu",
				"end": "4:15pm",
				"start": "3:10pm"
			},
			{
				"day": "We",
				"end": "3:00pm",
				"start": "1:50pm"
			},
			{
				"day": "Th",
				"end": "4:15pm",
				"start": "3:10pm"
			},
			{
				"day": "Fr",
				"end": "3:20pm",
				"start": "2:20pm"
			}
		]
	},
	"prerequisites": "Prerequisite: Arabic 101 or equivalent",
	"requirements": [],
	"scnc": null,
	"section": "00",
	"semester": "WI",
	"size": {
		"registered": 19,
		"total": 25,
		"waitlist": 0
	},
	"status": "Open",
	"subject": "ARBC",
	"summary": "This course sequence introduces non-Arabic speakers to the sounds, script, and basic grammar of Arabic--the language of 200 million speakers in the Arab world and the liturgical language of over a billion Muslims. Students will develop basic listening, speaking, reading and writing skills in Modern Standard Arabic. Classes will incorporate readings and audio-visual material from contemporary Arabic media, as well as popular music.",
	"synonym": "45741",
	"tags": [
		"MDLEPERT"
	],
	"title": "Elementary Arabic",
	"type": "Course",
	"year": 2017
}
