{
	"comments": [
		"2020-21 $345 fee"
	],
	"credits": 1.0,
	"id": "2021SP MUSC 153J.00",
	"instructors": [
		"Andrea Mazzariello"
	],
	"number": "153J",
	"offerings": null,
	"prerequisites": "Prerequisite: Music 220, or two courses from Music 221, 222 or 223 or instructor consent",
	"requirements": [
		"ARP"
	],
	"scnc": null,
	"section": "00",
	"semester": "SP",
	"size": {
		"registered": 5,
		"total": 4,
		"waitlist": 0
	},
	"status": "Closed",
	"subject": "MUSC",
	"summary": null,
	"synonym": "56561",
	"tags": [],
	"title": "Composition (Juried)",
	"type": "Juried",
	"year": 2021
}
