{
	"comments": [
		"Open only to participants in Pilgrimage and Sacred Space OCS Prog"
	],
	"credits": 6.0,
	"id": "2019SP JAPN 350.07",
	"instructors": [
		"Asuka Sango"
	],
	"number": "350",
	"offerings": null,
	"prerequisites": "Prerequisite: Japanese 206 or equivalent.",
	"requirements": [],
	"scnc": null,
	"section": "07",
	"semester": "SP",
	"size": {
		"registered": 0,
		"total": 25,
		"waitlist": 0
	},
	"status": "Open",
	"subject": "JAPN",
	"summary": null,
	"synonym": "52928",
	"tags": [
		"ASSTLANG",
		"EASTSUPP"
	],
	"title": "Pilgrimage & Sacred Space in Japan Program: Advanced Japanese through Place-Based Learning in Kyoto",
	"type": "Course",
	"year": 2019
}
