{
	"comments": [
		"Sophomore Priority, Material fees apply"
	],
	"credits": 6.0,
	"department": "ARTS",
	"id": "2001SP ARTS 110.02",
	"instructors": [
		"Kathryn Babcock"
	],
	"number": "110",
	"offerings": {
		"locations": [
			"Boliou 160"
		],
		"times": [
			{
				"day": "Tu",
				"end": "11:00am",
				"start": "8:30am"
			},
			{
				"day": "Th",
				"end": "11:00am",
				"start": "8:30am"
			}
		]
	},
	"prerequisites": null,
	"requirements": [],
	"scnc": null,
	"section": "02",
	"semester": "SP",
	"size": {
		"registered": 16,
		"total": 15,
		"waitlist": 0
	},
	"status": "Closed",
	"summary": null,
	"synonym": "754",
	"tags": [],
	"title": "Observational Drawing",
	"type": "Course",
	"year": 2001
}
