{
	"comments": [],
	"credits": 7.0,
	"department": "WGST",
	"id": "WGST 244.07",
	"instructors": [
		"Iveta Jusov\u00e1"
	],
	"number": "244.07",
	"offerings": null,
	"prerequisites": "<p class=\"prereq\">\n       <em>\n        Prerequisite:\n       </em>\n       Acceptance into the Carleton-Antioch Program required\n      </p>",
	"requirements": [],
	"scnc": null,
	"size": {
		"registered": 17,
		"total": 0,
		"waitlist": 0
	},
	"status": "Open",
	"summary": null,
	"synonym": "49659",
	"tags": [],
	"title": "Women's & Gender Studies in Europe Program: Issues in Feminist Methodologies"
}
