{
	"comments": [
		"OCS London Program"
	],
	"credits": 3.0,
	"id": "2020WI ENGL 279.07",
	"instructors": [
		"Constance Walker"
	],
	"number": "279",
	"offerings": null,
	"prerequisites": null,
	"requirements": [],
	"scnc": true,
	"section": "07",
	"semester": "WI",
	"size": {
		"registered": 11,
		"total": 25,
		"waitlist": 0
	},
	"status": "Open",
	"subject": "ENGL",
	"summary": null,
	"synonym": "52990",
	"tags": [
		"EUSTCNTRY"
	],
	"title": "London Program:  Urban Field Studies",
	"type": "Course",
	"year": 2020
}
