{
	"comments": [
		"Instr perm Second 5-week, Instructor Permission Required"
	],
	"credits": 3.0,
	"department": "BIOL",
	"id": "BIOL 354.00",
	"instructors": [
		"Charles E Crutchfield",
		"Debby R Walser-Kuntz"
	],
	"number": "354",
	"offerings": {
		"locations": [
			"Olin 101"
		],
		"times": [
			{
				"day": "We",
				"end": "6:00pm",
				"start": "3:00pm"
			}
		]
	},
	"prerequisites": "Prerequisite: Chemistry 233 and two upper division Biology courses (200 or 300-level) and instructor's permission required",
	"requirements": [],
	"scnc": true,
	"section": "00",
	"size": {
		"registered": 14,
		"total": 12,
		"waitlist": 0
	},
	"status": "Closed",
	"summary": "The course will cover the cellular and molecular biology of human skin in its normal and diseased states as it relates to a clinical presentation. Clinical dermatology and pathology will also be reviewed. The course style will be patterned along the lines as if it were a medical school course. Additionally, students will be introduced to many aspects of successfully negotiating medical school including introductions and possible \"field trips\" to the Mayo Clinic Medical School and/or University of Minnesota Medical School(s).",
	"synonym": "28741",
	"tags": [],
	"title": "Human Cutaneous Biology",
	"type": "Course"
}
