{
	"comments": [],
	"credits": 6.0,
	"department": "ASLN",
	"id": "ASLN 260.00",
	"instructors": [
		"Mark Hansell"
	],
	"number": "260.00",
	"offerings": {
		"locations": [
			"Scoville 106"
		],
		"times": [
			{
				"day": "Tu",
				"end": "3:00pm",
				"start": "1:15pm"
			},
			{
				"day": "Th",
				"end": "3:00pm",
				"start": "1:15pm"
			}
		]
	},
	"prerequisites": null,
	"requirements": [
		{
			"code": null,
			"name": "CL"
		}
	],
	"scnc": null,
	"size": {
		"registered": 12,
		"total": 25,
		"waitlist": 0
	},
	"status": "Open",
	"summary": null,
	"synonym": "10555",
	"tags": [
		{
			"code": "LINGPERT",
			"name": "Linguistics Pertinent Course"
		},
		{
			"code": "ASSTPERT",
			"name": "Asian Studies Pertinent"
		},
		{
			"code": "ASSTDISC",
			"name": "Asian Studies Disciplinary"
		},
		{
			"code": "ASSTSS",
			"name": "Asian Studies Social Science"
		},
		{
			"code": "ASSTEAST",
			"name": "Asian Studies East Asia"
		}
	],
	"title": "Historical Linguistics"
}
