{
	"comments": [],
	"credits": 6.0,
	"id": "2021SP GWSS 398.00",
	"instructors": [
		"Meera Sehgal"
	],
	"number": "398",
	"offerings": null,
	"prerequisites": "Prerequisite: Gender, Women's & Sexuality Studies 110 or 200, Women's & Gender Studies 110 or Instructor Consent",
	"requirements": [
		"SI",
		"WR2",
		"IS"
	],
	"scnc": null,
	"section": "00",
	"semester": "SP",
	"size": {
		"registered": 0,
		"total": 15,
		"waitlist": 0
	},
	"status": "Open",
	"subject": "GWSS",
	"summary": null,
	"synonym": "59724",
	"tags": [],
	"title": "Transnational Feminist Activism",
	"type": "Course",
	"year": 2021
}
