{
	"comments": [
		"Instructor Permission Required"
	],
	"credits": 0.0,
	"department": "PE",
	"id": "PE 282.01",
	"instructors": [
		"Stephan G Zweifel"
	],
	"number": "282",
	"offerings": null,
	"prerequisites": null,
	"requirements": [
		"PEI"
	],
	"scnc": true,
	"section": "01",
	"semester": "WI",
	"size": {
		"registered": 1,
		"total": 1,
		"waitlist": 0
	},
	"status": "Closed",
	"summary": null,
	"synonym": "51454",
	"tags": [],
	"title": "Tennis Intercollegiate, Men",
	"type": "Course",
	"year": 2018
}
