{
	"comments": [],
	"credits": 6.0,
	"department": "PHIL",
	"id": "PHIL 274.00",
	"instructors": [
		"Roy Elveton"
	],
	"number": "274",
	"offerings": {
		"locations": [
			"Leighton 301"
		],
		"times": [
			{
				"day": "Tu",
				"end": "4:15pm",
				"start": "2:30pm"
			},
			{
				"day": "Th",
				"end": "4:15pm",
				"start": "2:30pm"
			}
		]
	},
	"prerequisites": null,
	"requirements": [],
	"scnc": null,
	"section": "00",
	"semester": "WI",
	"size": {
		"registered": 4,
		"total": 25,
		"waitlist": 0
	},
	"status": "Open",
	"summary": null,
	"synonym": "2033",
	"tags": [],
	"title": "Continental Philosophy",
	"type": "Course",
	"year": 2000
}
