{
	"comments": [
		"Soph prio GEOL 110L-53 or 54 required"
	],
	"credits": 6.0,
	"department": "GEOL",
	"id": "2006FA GEOL 110.02",
	"instructors": [
		"Cameron Davidson"
	],
	"number": "110",
	"offerings": {
		"locations": [
			"Mudd 66"
		],
		"times": [
			{
				"day": "Mo",
				"end": "11:00am",
				"start": "9:50am"
			},
			{
				"day": "We",
				"end": "11:00am",
				"start": "9:50am"
			},
			{
				"day": "Fr",
				"end": "10:40am",
				"start": "9:40am"
			}
		]
	},
	"prerequisites": null,
	"requirements": [],
	"scnc": null,
	"section": "02",
	"semester": "FA",
	"size": {
		"registered": 35,
		"total": 36,
		"waitlist": 0
	},
	"status": "Open",
	"summary": null,
	"synonym": "15385",
	"tags": [],
	"title": "Introduction to Geology",
	"type": "Course",
	"year": 2006
}
