{
	"comments": [],
	"credits": 6.0,
	"id": "2021WI MATH 321.00",
	"instructors": [
		"Kate J Meyer"
	],
	"number": "321",
	"offerings": {
		"locations": [],
		"times": [
			{
				"day": "Mo",
				"end": "11:10am",
				"start": "10:00am"
			},
			{
				"day": "We",
				"end": "11:10am",
				"start": "10:00am"
			},
			{
				"day": "Fr",
				"end": "10:50am",
				"start": "9:50am"
			}
		]
	},
	"prerequisites": "Prerequisite: Mathematics 236 or instructor permission",
	"requirements": [
		"FSR"
	],
	"scnc": null,
	"section": "00",
	"semester": "WI",
	"size": {
		"registered": 24,
		"total": 25,
		"waitlist": 0
	},
	"status": "Open",
	"subject": "MATH",
	"summary": "A systematic study of concepts basic to calculus, such as topology of the real numbers, limits, differentiation, integration, convergence of sequences, and series of functions.",
	"synonym": "58684",
	"tags": [],
	"title": "Real Analysis I",
	"type": "Course",
	"year": 2021
}
