{
	"comments": [],
	"credits": 0.0,
	"id": "2019FA PE 158.04",
	"instructors": [
		"Tammy Metcalf-Filzen"
	],
	"number": "158",
	"offerings": {
		"locations": [
			"Recreation Center WALL"
		],
		"times": [
			{
				"day": "Tu",
				"end": "2:20pm",
				"start": "1:15pm"
			},
			{
				"day": "Th",
				"end": "2:20pm",
				"start": "1:15pm"
			}
		]
	},
	"prerequisites": null,
	"requirements": [
		"PE"
	],
	"scnc": true,
	"section": "04",
	"semester": "FA",
	"size": {
		"registered": 0,
		"total": 12,
		"waitlist": 0
	},
	"status": "Open",
	"subject": "PE",
	"summary": null,
	"synonym": "55882",
	"tags": [],
	"title": "Rock Climbing",
	"type": "Course",
	"year": 2019
}
