{
	"comments": [],
	"credits": 6.0,
	"id": "2021WI SOAN 208.00",
	"instructors": [
		"Colin McLaughlin-Alcock"
	],
	"number": "208",
	"offerings": {
		"locations": [],
		"times": [
			{
				"day": "Mo",
				"end": "2:10pm",
				"start": "1:00pm"
			},
			{
				"day": "We",
				"end": "2:10pm",
				"start": "1:00pm"
			},
			{
				"day": "Fr",
				"end": "2:50pm",
				"start": "1:50pm"
			}
		]
	},
	"prerequisites": "Prerequisite: The department strongly recommends that Sociology/Anthropology 110 or 111 be taken prior to enrolling in courses numbered 200 or above",
	"requirements": [
		"SI",
		"IS"
	],
	"scnc": null,
	"section": "00",
	"semester": "WI",
	"size": {
		"registered": 22,
		"total": 25,
		"waitlist": 3
	},
	"status": "Closed",
	"subject": "SOAN",
	"summary": null,
	"synonym": "59596",
	"tags": [],
	"title": "Gentrification",
	"type": "Course",
	"year": 2021
}
