{
	"comments": [
		"BIOL 232 required"
	],
	"credits": 2.0,
	"department": "BIOL",
	"id": "BIOL 233.02",
	"instructors": [
		"Amy H Moore"
	],
	"number": "233.02",
	"offerings": {
		"locations": [
			"Hulings 215"
		],
		"times": [
			{
				"day": "Th",
				"end": "5:00pm",
				"start": "1:00pm"
			}
		]
	},
	"prerequisites": "None",
	"requirements": [],
	"scnc": null,
	"size": {
		"registered": 17,
		"total": 18,
		"waitlist": 0
	},
	"status": "Open",
	"summary": null,
	"synonym": "35233",
	"tags": [],
	"title": "Human Physiology Lab"
}
