{
	"comments": [],
	"credits": 2.0,
	"department": "GRK",
	"id": "GRK 285.00",
	"instructors": [
		"Clara S Hardy"
	],
	"number": "285.00",
	"offerings": {
		"locations": [
			"Language & Dining Center 202"
		],
		"times": [
			{
				"day": "We",
				"end": "4:20pm",
				"start": "3:10pm"
			}
		]
	},
	"prerequisites": "Prerequisite: Greek 204 or equivalent",
	"requirements": [],
	"scnc": true,
	"size": {
		"registered": 1,
		"total": 25,
		"waitlist": 0
	},
	"status": "Open",
	"summary": null,
	"synonym": "52325",
	"tags": [],
	"title": "Weekly Greek"
}
