{
	"comments": [],
	"credits": 6.0,
	"id": "2017FA ENGL 222.00",
	"instructors": [
		"Susan Jaret McKinstry"
	],
	"number": "222",
	"offerings": {
		"locations": [
			"Laird 212"
		],
		"times": [
			{
				"day": "Tu",
				"end": "3:00pm",
				"start": "1:15pm"
			},
			{
				"day": "Th",
				"end": "3:00pm",
				"start": "1:15pm"
			}
		]
	},
	"prerequisites": null,
	"requirements": [
		"LA",
		"WR2"
	],
	"scnc": null,
	"section": "00",
	"semester": "FA",
	"size": {
		"registered": 21,
		"total": 25,
		"waitlist": 0
	},
	"status": "Open",
	"subject": "ENGL",
	"summary": "All of Jane Austen's fiction will be read; the works she did not complete or choose to publish during her lifetime will be studied in an attempt to understand the art of her mature comic masterpieces,",
	"synonym": "48520",
	"tags": [
		"ENGLHE2",
		"ENGLT1",
		"EUSTCNTRY"
	],
	"title": "The Art of Jane Austen",
	"type": "Course",
	"year": 2017
}
