{
	"comments": [
		"Sophomore Priority"
	],
	"credits": 6.0,
	"id": "2021SP ENGL 266.00",
	"instructors": [
		"George Cusack"
	],
	"number": "266",
	"offerings": {
		"locations": [
			"Weitz Center 133"
		],
		"times": [
			{
				"day": "Tu",
				"end": "12:05pm",
				"start": "10:20am"
			},
			{
				"day": "Th",
				"end": "12:05pm",
				"start": "10:20am"
			}
		]
	},
	"prerequisites": null,
	"requirements": [
		"WR2"
	],
	"scnc": null,
	"section": "00",
	"semester": "SP",
	"size": {
		"registered": 9,
		"total": 15,
		"waitlist": 0
	},
	"status": "Open",
	"subject": "ENGL",
	"summary": null,
	"synonym": "59754",
	"tags": [],
	"title": "Research Writing",
	"type": "Course",
	"year": 2021
}
