{
	"comments": [],
	"credits": 1.0,
	"department": "PSYC",
	"id": "PSYC 400.06",
	"instructors": [
		"Julie J Neiworth"
	],
	"number": "400.06",
	"offerings": null,
	"prerequisites": "<p class=\"prereq\">\n       <em>\n        Prerequisite:\n       </em>\n       Psychology 397, 398, or 399.\n      </p>",
	"requirements": [],
	"scnc": true,
	"size": {
		"registered": 3,
		"total": 12,
		"waitlist": 0
	},
	"status": "Open",
	"summary": null,
	"synonym": "45943",
	"tags": [],
	"title": "Integrative Exercise"
}
