{
	"comments": [],
	"credits": 6.0,
	"id": "2018SP SOAN 263.00",
	"instructors": [
		"Ahmed S Ibrahim"
	],
	"number": "263",
	"offerings": {
		"locations": [
			"Leighton 426"
		],
		"times": [
			{
				"day": "Tu",
				"end": "4:55pm",
				"start": "3:10pm"
			},
			{
				"day": "Th",
				"end": "4:55pm",
				"start": "3:10pm"
			}
		]
	},
	"prerequisites": "Prerequisite: Previous courses in anthropology or religion would offer helpful background, but are not required.",
	"requirements": [
		"SI",
		"WR2",
		"IDS"
	],
	"scnc": null,
	"section": "00",
	"semester": "SP",
	"size": {
		"registered": 21,
		"total": 25,
		"waitlist": 0
	},
	"status": "Open",
	"subject": "SOAN",
	"summary": null,
	"synonym": "49600",
	"tags": [
		"MESTGRP1",
		"AFSTSI",
		"POSI-LPS2",
		"AMSTAMERWRLD",
		"AMSTDAC"
	],
	"title": "Terrorism",
	"type": "Course",
	"year": 2018
}
