{
	"comments": [
		"Paris Program"
	],
	"credits": 6.0,
	"department": "FREN",
	"id": "FREN 246.07",
	"instructors": [
		"",
		"Éva S Pósfay"
	],
	"number": "246",
	"offerings": null,
	"prerequisites": null,
	"requirements": [],
	"scnc": null,
	"section": "07",
	"size": {
		"registered": 17,
		"total": 25,
		"waitlist": 0
	},
	"status": "Open",
	"summary": null,
	"synonym": "13470",
	"tags": [
		"FRSTELECAL",
		"FRSTELEC",
		"EUSTOFFCAMP",
		"EUSTCNTRY"
	],
	"title": "City of Wonder: Paris in Arts",
	"type": "Course"
}
