{
	"comments": [],
	"credits": 1.0,
	"department": "MUSC",
	"id": "MUSC 189.00",
	"instructors": [
		"Bruce P Gleason"
	],
	"number": "189",
	"offerings": {
		"locations": [
			"Music & Drama Center LL05"
		],
		"times": [
			{
				"day": "Mo",
				"end": "5:00pm",
				"start": "3:30pm"
			},
			{
				"day": "We",
				"end": "5:00pm",
				"start": "3:30pm"
			},
			{
				"day": "Fr",
				"end": "5:00pm",
				"start": "3:30pm"
			}
		]
	},
	"prerequisites": null,
	"requirements": [],
	"scnc": true,
	"section": "00",
	"semester": "SP",
	"size": {
		"registered": 25,
		"total": 100,
		"waitlist": 0
	},
	"status": "Open",
	"summary": null,
	"synonym": "1908",
	"tags": [],
	"title": "Symphonic Wind Ensemble",
	"type": "Course",
	"year": 2002
}
