{
	"comments": [
		"Instructor Permission Required"
	],
	"credits": 0.0,
	"id": "2007WI PE 273.00",
	"instructors": [
		"Andy M Clark"
	],
	"number": "273",
	"offerings": null,
	"prerequisites": null,
	"requirements": [
		"PEI"
	],
	"scnc": true,
	"section": "00",
	"semester": "WI",
	"size": {
		"registered": 34,
		"total": 30,
		"waitlist": 0
	},
	"status": "Closed",
	"subject": "PE",
	"summary": null,
	"synonym": "17124",
	"tags": [],
	"title": "Swimng/Diving Intercollegiate",
	"type": "Course",
	"year": 2007
}
