{
	"comments": [],
	"credits": 0.0,
	"department": "PE",
	"id": "PE 170.00",
	"instructors": [
		"Sarah E Hurst"
	],
	"number": "170",
	"offerings": {
		"locations": [
			"Recreation Center 117"
		],
		"times": [
			{
				"day": "Tu",
				"end": "11:50am",
				"start": "10:45am"
			},
			{
				"day": "Th",
				"end": "11:50am",
				"start": "10:45am"
			}
		]
	},
	"prerequisites": null,
	"requirements": [
		"PE"
	],
	"scnc": true,
	"section": "00",
	"semester": "WI",
	"size": {
		"registered": 9,
		"total": 12,
		"waitlist": 0
	},
	"status": "Open",
	"summary": null,
	"synonym": "5173",
	"tags": [],
	"title": "Squash",
	"type": "Course",
	"year": 2003
}
