{
	"comments": [
		"X-List CHEM 128L Soph Prio",
		"Cross-listed with CHEM 128L.57"
	],
	"credits": 0.0,
	"department": "ENTS",
	"id": "2001SP ENTS 128L.57",
	"instructors": [
		"Will Hollingsworth"
	],
	"number": "128L",
	"offerings": {
		"locations": [
			"Mudd 260"
		],
		"times": [
			{
				"day": "Tu",
				"end": "12:30pm",
				"start": "8:30am"
			}
		]
	},
	"prerequisites": null,
	"requirements": [],
	"scnc": null,
	"section": "57",
	"semester": "SP",
	"size": {
		"registered": 14,
		"total": 20,
		"waitlist": 0
	},
	"status": "Open",
	"summary": null,
	"synonym": "1607",
	"tags": [],
	"title": "Principles-Environ Chem Lab",
	"type": "Lab",
	"year": 2001
}
