{
	"comments": [],
	"credits": 3.0,
	"department": "GERM",
	"id": "GERM 261.00",
	"instructors": [
		"Kai Herklotz"
	],
	"number": "261.00",
	"offerings": {
		"locations": [
			"Weitz Center 132"
		],
		"times": [
			{
				"day": "Mo",
				"end": "3:00pm",
				"start": "1:50pm"
			},
			{
				"day": "We",
				"end": "3:00pm",
				"start": "1:50pm"
			}
		]
	},
	"prerequisites": "<p class=\"prereq\">\n       <em>\n        Prerequisite:\n       </em>\n       German 204. Recommended preparation: at least one course above German 204.\n      </p>",
	"requirements": [
		{
			"code": "LA",
			"name": "Literary/Artistic Analysis"
		},
		{
			"code": "IS",
			"name": "International Studies"
		}
	],
	"scnc": null,
	"size": {
		"registered": 8,
		"total": 25,
		"waitlist": 0
	},
	"status": "Open",
	"summary": null,
	"synonym": "33106",
	"tags": [
		{
			"code": "EUSTCNTRY",
			"name": "EUST Country Specific Course"
		}
	],
	"title": "Contemporary German Fiction"
}
