{
	"comments": [],
	"credits": 6.0,
	"department": "SPAN",
	"id": "SPAN 350.00",
	"instructors": [
		"Becky Boling"
	],
	"number": "350",
	"offerings": {
		"locations": [
			"Language & Dining Center 205"
		],
		"times": [
			{
				"day": "Mo",
				"end": "11:00am",
				"start": "9:50am"
			},
			{
				"day": "We",
				"end": "11:00am",
				"start": "9:50am"
			},
			{
				"day": "Fr",
				"end": "10:40am",
				"start": "9:40am"
			}
		]
	},
	"prerequisites": "Prerequisite: Spanish 205 or above",
	"requirements": [
		"LA",
		"IS"
	],
	"scnc": null,
	"section": "00",
	"semester": "WI",
	"size": {
		"registered": 8,
		"total": 25,
		"waitlist": 0
	},
	"status": "Open",
	"summary": "Postboom narratives question the very nature of telling stories, from Rigoberta Menchú's testimony of genocide to the virtual reality of MacOndo. Eduardo Galeano, Manuel Puig, and Elena Poniatowska are some of the writers we will examine, writers who combine fiction and reportage, recontextualize the",
	"synonym": "26648",
	"tags": [
		"ENGLFORLIT",
		"CCSTETHNIC",
		"LITFORLANG",
		"LTAMLIT",
		"LTAMELECTIVE",
		"LTAMPERT",
		"LTAM300LIT",
		"ENGLLOE"
	],
	"title": "Recent Trends in Latin American Narrative: Pop Culture and Testimony",
	"type": "Course",
	"year": 2011
}
