{
	"comments": [
		"Extra Time required. Evening Screenings."
	],
	"credits": 6.0,
	"department": "CAMS",
	"id": "CAMS 225.00",
	"instructors": [
		"Carol Donelan"
	],
	"number": "225.00",
	"offerings": {
		"locations": [
			"Weitz Center 132"
		],
		"times": [
			{
				"day": "Tu",
				"end": "3:00pm",
				"start": "1:15pm"
			},
			{
				"day": "Th",
				"end": "3:00pm",
				"start": "1:15pm"
			}
		]
	},
	"prerequisites": null,
	"requirements": [
		{
			"code": "LA",
			"name": "Literary/Artistic Analysis"
		},
		{
			"code": "IDS",
			"name": "Intercultural Domestic Studies"
		}
	],
	"scnc": null,
	"size": {
		"registered": 24,
		"total": 25,
		"waitlist": 0
	},
	"status": "Closed",
	"summary": null,
	"synonym": "49159",
	"tags": [
		{
			"code": "CAMSELECTIVE",
			"name": "CAMS Elective"
		},
		{
			"code": "AMSTTOPICAL1",
			"name": "AMST Group I Topical"
		},
		{
			"code": "WGSTADDL",
			"name": "WGST Additional Credits"
		}
	],
	"title": "Film Noir: The Dark Side of the American Dream"
}
