{
	"comments": [],
	"credits": 2.0,
	"id": "2020FA SPAN 209.00",
	"instructors": [
		"Palmar M Alvarez-Blanco"
	],
	"number": "209",
	"offerings": {
		"locations": [],
		"times": [
			{
				"day": "Mo",
				"end": "11:10am",
				"start": "10:00am"
			}
		]
	},
	"prerequisites": "Prerequisite: Spanish 204 or equivalent",
	"requirements": [
		"HI",
		"IS"
	],
	"scnc": true,
	"section": "00",
	"semester": "FA",
	"size": {
		"registered": 7,
		"total": 10,
		"waitlist": 0
	},
	"status": "Closed",
	"subject": "SPAN",
	"summary": null,
	"synonym": "56200",
	"tags": [],
	"title": "Radio and News in Spanish",
	"type": "Course",
	"year": 2020
}
