{
	"comments": [],
	"credits": 6.0,
	"department": "POSC",
	"id": "POSC 308.00",
	"instructors": [
		"Richard A Keiser"
	],
	"number": "308.00",
	"offerings": {
		"locations": [
			"Library 344"
		],
		"times": [
			{
				"day": "Tu",
				"end": "3:00pm",
				"start": "1:15pm"
			},
			{
				"day": "Th",
				"end": "3:00pm",
				"start": "1:15pm"
			}
		]
	},
	"prerequisites": null,
	"requirements": [],
	"scnc": null,
	"size": {
		"registered": 7,
		"total": 15,
		"waitlist": 0
	},
	"status": "Open",
	"summary": null,
	"synonym": "9740",
	"tags": [
		{
			"code": "AMSTTOPICAL3",
			"name": "AMST Group III Topical"
		},
		{
			"code": "AFAMDISTROSS",
			"name": "AFAM Distro Social Sciences"
		}
	],
	"title": "Poverty and Public Policy"
}
