{
	"comments": [
		"WR"
	],
	"credits": 6.0,
	"department": "ENGL",
	"id": "ENGL 110.00",
	"instructors": [
		"George G Shuffelton"
	],
	"number": "110",
	"offerings": {
		"locations": [
			"Laird 212"
		],
		"times": [
			{
				"day": "Mo",
				"end": "11:00am",
				"start": "9:50am"
			},
			{
				"day": "We",
				"end": "11:00am",
				"start": "9:50am"
			},
			{
				"day": "Fr",
				"end": "10:40am",
				"start": "9:40am"
			}
		]
	},
	"prerequisites": null,
	"requirements": [],
	"scnc": null,
	"section": "00",
	"size": {
		"registered": 17,
		"total": 25,
		"waitlist": 0
	},
	"status": "Open",
	"summary": null,
	"synonym": "3996",
	"tags": [
		"LITFORLANG",
		"EUSTCNTRY",
		"MARSCORE",
		"MARSSUPP"
	],
	"title": "English Literature I",
	"type": "Course"
}
