{
	"comments": [
		"Cross-listed with PE 107"
	],
	"credits": 1.0,
	"department": "DANC",
	"id": "DANC 107.00",
	"instructors": [
		"Jennifer Bader"
	],
	"number": "107",
	"offerings": {
		"locations": [
			"Recreation Center STU"
		],
		"times": [
			{
				"day": "Mo",
				"end": "11:00am",
				"start": "9:50am"
			},
			{
				"day": "We",
				"end": "11:00am",
				"start": "9:50am"
			}
		]
	},
	"prerequisites": null,
	"requirements": [],
	"scnc": true,
	"section": "00",
	"size": {
		"registered": 13,
		"total": 25,
		"waitlist": 0
	},
	"status": "Open",
	"summary": null,
	"synonym": "21362",
	"tags": [],
	"title": "Ballet I",
	"type": "Course"
}
