{
	"comments": [],
	"credits": 6.0,
	"id": "2021WI PHIL 303.00",
	"instructors": [
		"Anna Moltchanova"
	],
	"number": "303",
	"offerings": {
		"locations": [
			"Weitz Center 235"
		],
		"times": [
			{
				"day": "Tu",
				"end": "8:45pm",
				"start": "7:00pm"
			},
			{
				"day": "Th",
				"end": "8:45pm",
				"start": "7:00pm"
			}
		]
	},
	"prerequisites": "Prerequisite: One Previous Philosophy course or instructor permission",
	"requirements": [
		"HI",
		"WR2",
		"IDS",
		"QRE"
	],
	"scnc": null,
	"section": "00",
	"semester": "WI",
	"size": {
		"registered": 16,
		"total": 15,
		"waitlist": 0
	},
	"status": "Closed",
	"subject": "PHIL",
	"summary": null,
	"synonym": "59662",
	"tags": [
		"PHILTHEORY",
		"CGSCELECTIVE"
	],
	"title": "Bias, Belief, Community, Emotion",
	"type": "Course",
	"year": 2021
}
