{
	"comments": [],
	"credits": 6.0,
	"department": "ENGL",
	"id": "ENGL 332.00",
	"instructors": [
		"Michael J Kowalewski"
	],
	"number": "332.00",
	"offerings": {
		"locations": [
			"Laird 211"
		],
		"times": [
			{
				"day": "Mo",
				"end": "1:40pm",
				"start": "12:30pm"
			},
			{
				"day": "We",
				"end": "1:40pm",
				"start": "12:30pm"
			},
			{
				"day": "Fr",
				"end": "2:10pm",
				"start": "1:10pm"
			}
		]
	},
	"prerequisites": "Prerequisite: One English foundations course and one additional 6 credit English course",
	"requirements": [
		{
			"code": "LA",
			"name": "Literary/Artistic Analysis"
		},
		{
			"code": "WR2",
			"name": "Writing Rich 2"
		}
	],
	"scnc": null,
	"size": {
		"registered": 21,
		"total": 20,
		"waitlist": 0
	},
	"status": "Closed",
	"summary": null,
	"synonym": "48555",
	"tags": [
		{
			"code": "ENGLT2",
			"name": "ENGL Tradition 2"
		},
		{
			"code": "ENGLHE3",
			"name": "ENGL Hist Era 3"
		},
		{
			"code": "AMSTTOPICAL1",
			"name": "AMST Group I Topical"
		},
		{
			"code": "LITFORLANG",
			"name": "Literature for Languages"
		},
		{
			"code": "AMSTPCC",
			"name": "Amst Prodctn Consmptn Culture"
		}
	],
	"title": "Studies in American Literature: Faulkner, Hemingway, and Fitzgerald"
}
