{
	"comments": [],
	"credits": 6.0,
	"department": "MATH",
	"id": "MATH 236.00",
	"instructors": [
		"Deanna Haunsperger"
	],
	"number": "236",
	"offerings": {
		"locations": [
			"CMC 319"
		],
		"times": [
			{
				"day": "Mo",
				"end": "11:00am",
				"start": "9:50am"
			},
			{
				"day": "We",
				"end": "11:00am",
				"start": "9:50am"
			},
			{
				"day": "Fr",
				"end": "10:40am",
				"start": "9:40am"
			}
		]
	},
	"prerequisites": null,
	"requirements": [],
	"scnc": null,
	"section": "00",
	"semester": "WI",
	"size": {
		"registered": 11,
		"total": 28,
		"waitlist": 0
	},
	"status": "Open",
	"summary": null,
	"synonym": "12347",
	"tags": [],
	"title": "Mathematical Structures",
	"type": "Course",
	"year": 2006
}
