{
	"comments": [
		"Instructor Permission Required"
	],
	"credits": 0.0,
	"department": "PE",
	"id": "2001WI PE 211.00",
	"instructors": [
		"Guy A Kalland"
	],
	"number": "211",
	"offerings": null,
	"prerequisites": null,
	"requirements": [
		"PEI"
	],
	"scnc": true,
	"section": "00",
	"semester": "WI",
	"size": {
		"registered": 12,
		"total": 0,
		"waitlist": 0
	},
	"status": "Closed",
	"summary": null,
	"synonym": "975",
	"tags": [],
	"title": "Basketball Intercollegiate",
	"type": "Course",
	"year": 2001
}
