{
	"comments": [
		"Northfield Ice Arena."
	],
	"credits": 0.0,
	"id": "2012WI PE 232.00",
	"instructors": [
		"Aaron J Chaput"
	],
	"number": "232",
	"offerings": null,
	"prerequisites": null,
	"requirements": [
		"PEC"
	],
	"scnc": true,
	"section": "00",
	"semester": "WI",
	"size": {
		"registered": 11,
		"total": 50,
		"waitlist": 0
	},
	"status": "Open",
	"subject": "PE",
	"summary": null,
	"synonym": "28461",
	"tags": [],
	"title": "Ice Hockey Club, Women",
	"type": "Course",
	"year": 2012
}
