{
	"comments": [
		"Not open to first year students."
	],
	"credits": 6.0,
	"department": "POSC",
	"id": "POSC 218.00",
	"instructors": [
		"Richard A Keiser"
	],
	"number": "218.00",
	"offerings": {
		"locations": [
			"Weitz Center 136"
		],
		"times": [
			{
				"day": "Mo",
				"end": "11:00am",
				"start": "9:50am"
			},
			{
				"day": "We",
				"end": "11:00am",
				"start": "9:50am"
			},
			{
				"day": "Fr",
				"end": "10:40am",
				"start": "9:40am"
			}
		]
	},
	"prerequisites": "Prerequisite: Sophomore Standing",
	"requirements": [
		{
			"code": "SI",
			"name": "Social Inquiry"
		},
		{
			"code": "IDS",
			"name": "Intercultural Domestic Studies"
		}
	],
	"scnc": null,
	"size": {
		"registered": 13,
		"total": 25,
		"waitlist": 0
	},
	"status": "Open",
	"summary": "What can scholarship tell us about educational strategies to reduce achievement gaps and economic opportunity? Do the policies promoted at the city, state and federal levels reflect that knowledge? How are these policies made? What is the relationship between schools and the economic class, racial composition and housing stock of their neighborhoods?",
	"synonym": "33047",
	"tags": [
		{
			"code": "POSI-DSS2",
			"name": "Democracy, Society & State 2"
		},
		{
			"code": "AMSTTOPICAL3",
			"name": "AMST Group III Topical"
		},
		{
			"code": "POSI-DSS",
			"name": "Democracy, Society & State"
		},
		{
			"code": "POSIELECTIVE",
			"name": "Polisci/Ir Elective"
		},
		{
			"code": "EDUCPERT",
			"name": "Educational Studies Pertinent"
		}
	],
	"title": "Schools, Scholarship and Policy in the United States"
}
