{
	"comments": [
		"PHYS 261 required"
	],
	"credits": 0.0,
	"department": "PHYS",
	"id": "2010FA PHYS 261L.59",
	"instructors": [
		"Nelson L Christensen"
	],
	"number": "261L",
	"offerings": {
		"locations": [
			"Olin 210"
		],
		"times": [
			{
				"day": "Th",
				"end": "12:00pm",
				"start": "8:00am"
			}
		]
	},
	"prerequisites": null,
	"requirements": [],
	"scnc": null,
	"section": "59",
	"semester": "FA",
	"size": {
		"registered": 7,
		"total": 12,
		"waitlist": 0
	},
	"status": "Open",
	"summary": null,
	"synonym": "25995",
	"tags": [],
	"title": "Medical Physics Lab",
	"type": "Lab",
	"year": 2010
}
