{
	"comments": [
		"X-List ENGL 230, AMST 230",
		"Cross-listed with ENGL 230.00"
	],
	"credits": 6.0,
	"department": "AFAM",
	"id": "AFAM 230.00",
	"instructors": [
		"Kofi Owusu"
	],
	"number": "230.00",
	"offerings": {
		"locations": [
			"Laird 212"
		],
		"times": [
			{
				"day": "Tu",
				"end": "12:15pm",
				"start": "10:30am"
			},
			{
				"day": "Th",
				"end": "12:15pm",
				"start": "10:30am"
			}
		]
	},
	"prerequisites": null,
	"requirements": [],
	"scnc": null,
	"size": {
		"registered": 20,
		"total": 25,
		"waitlist": 0
	},
	"status": "Open",
	"summary": null,
	"synonym": "2710",
	"tags": [
		"ENGL4",
		"AMSTTOPICAL1",
		"CCSTETHNIC",
		"LITFORLANG",
		"AFAMDISTROAL"
	],
	"title": "African American Autobiography"
}
